irfundusset/__init__.py
irfundusset/config.ini
irfundusset/config.py
irfundusset/curated_master_listing.fdd
irfundusset/data_source.py
irfundusset/data_source_parsers.py
irfundusset/datastore.py
irfundusset/irfundusset_cmd.py
irfundusset/meta_cohorts.ini
irfundusset/utils.py
irfundusset/cohort_parsers/__init__.py
irfundusset/cohort_parsers/cataracts.py
irfundusset/cohort_parsers/chasedb.py
irfundusset/cohort_parsers/commonz.py
irfundusset/cohort_parsers/eyepacs.py
irfundusset/cohort_parsers/five.py
irfundusset/cohort_parsers/hrf.py
irfundusset/cohort_parsers/idrid.py
irfundusset/cohort_parsers/kaggle1000.py
irfundusset/cohort_parsers/odrid.py
irfundusset/cohort_parsers/papila.py
irfundusset/cohort_parsers/stare.py
irfundusset-1.0.0.dist-info/METADATA
irfundusset-1.0.0.dist-info/WHEEL
irfundusset-1.0.0.dist-info/licenses/License.txt
irfundusset-1.0.0.dist-info/RECORD
