Metadata-Version: 2.4
Name: irfundusset
Version: 1.0.0
Summary: The Integrated Retinal Fundus Set (IRFundusSet) systematically integrates 46,064 RFPs from ten distinct public sources into a unified structure, implementing essential methodological steps to enable collation of archives, standardization of image pixel data, and seamless integration into a modelling pipeline.
Project-URL: Homepage, https://github.com/bilha-analytics/IRFundusSet/
Project-URL: Issues, https://github.com/bilha-analytics/IRFundusSet/issues
Author-email: "P.Bilha Githinji" <bilha.analytics@gmail.com>
License-Expression: MIT
License-File: License.txt
Keywords: image dataset,retinal fundus
Classifier: Operating System :: OS Independent
Classifier: Programming Language :: Python :: 3
Requires-Python: >=3.9
Requires-Dist: numpy>=2.0.0
Requires-Dist: opencv-python-headless>=4.9.0.80
Requires-Dist: pandas>=2.1.4
Requires-Dist: scikit-image>=0.22.0
Requires-Dist: tqdm>=4.65.0
